MANIFEST.in
README.txt
setup.py
XStatic_MarkitUp.egg-info/PKG-INFO
XStatic_MarkitUp.egg-info/SOURCES.txt
XStatic_MarkitUp.egg-info/dependency_links.txt
XStatic_MarkitUp.egg-info/namespace_packages.txt
XStatic_MarkitUp.egg-info/not-zip-safe
XStatic_MarkitUp.egg-info/top_level.txt
xstatic/__init__.py
xstatic/pkg/__init__.py
xstatic/pkg/markitup/.DS_Store
xstatic/pkg/markitup/__init__.py
xstatic/pkg/markitup/data/.DS_Store
xstatic/pkg/markitup/data/jquery.markitup.js
xstatic/pkg/markitup/data/js/.DS_Store
xstatic/pkg/markitup/data/js/markdown/set.js
xstatic/pkg/markitup/data/js/wiki_creole/set.js
xstatic/pkg/markitup/data/js/wiki_mediawiki/set.js
xstatic/pkg/markitup/data/js/wiki_moinmoin/set.js
xstatic/pkg/markitup/data/sets/.DS_Store
xstatic/pkg/markitup/data/sets/default/.DS_Store
xstatic/pkg/markitup/data/sets/default/style.css
xstatic/pkg/markitup/data/sets/default/images/bold.png
xstatic/pkg/markitup/data/sets/default/images/clean.png
xstatic/pkg/markitup/data/sets/default/images/image.png
xstatic/pkg/markitup/data/sets/default/images/italic.png
xstatic/pkg/markitup/data/sets/default/images/link.png
xstatic/pkg/markitup/data/sets/default/images/list-bullet.png
xstatic/pkg/markitup/data/sets/default/images/list-numeric.png
xstatic/pkg/markitup/data/sets/default/images/picture.png
xstatic/pkg/markitup/data/sets/default/images/preview.png
xstatic/pkg/markitup/data/sets/default/images/stroke.png
xstatic/pkg/markitup/data/sets/markdown/.DS_Store
xstatic/pkg/markitup/data/sets/markdown/readme.txt
xstatic/pkg/markitup/data/sets/markdown/style.css
xstatic/pkg/markitup/data/sets/markdown/images/bold.png
xstatic/pkg/markitup/data/sets/markdown/images/code.png
xstatic/pkg/markitup/data/sets/markdown/images/h1.png
xstatic/pkg/markitup/data/sets/markdown/images/h2.png
xstatic/pkg/markitup/data/sets/markdown/images/h3.png
xstatic/pkg/markitup/data/sets/markdown/images/h4.png
xstatic/pkg/markitup/data/sets/markdown/images/h5.png
xstatic/pkg/markitup/data/sets/markdown/images/h6.png
xstatic/pkg/markitup/data/sets/markdown/images/italic.png
xstatic/pkg/markitup/data/sets/markdown/images/link.png
xstatic/pkg/markitup/data/sets/markdown/images/list-bullet.png
xstatic/pkg/markitup/data/sets/markdown/images/list-numeric.png
