Metadata-Version: 1.0
Name: XStatic-MarkitUp
Version: 1.1.14.1
Summary: MarkitUp 1.1.14 (XStatic packaging standard)
Home-page: http://markitup.jaysalvat.com/home/
Author: Yask Srivastava
Author-email: yask123@gmail.com
License: (same as MarkitUp)
Keywords: markitup xstatic
Platform: any
